deebase/__init__.py
deebase/admin/__init__.py
deebase/admin/renderers.py
deebase/admin/router.py
deebase/admin/templates/base.html
deebase/admin/templates/create.html
deebase/admin/templates/dashboard.html
deebase/admin/templates/delete.html
deebase/admin/templates/edit.html
deebase/admin/templates/list.html
deebase/admin/templates/view.html
deebase/api/__init__.py
deebase/api/docs.py
deebase/api/exceptions.py
deebase/api/models.py
deebase/api/router.py
deebase/api/validators.py
deebase/cli/__init__.py
deebase/cli/api_cmd.py
deebase/cli/backup.py
deebase/cli/codegen_cmd.py
deebase/cli/data_cmd.py
deebase/cli/db_cmd.py
deebase/cli/generator.py
deebase/cli/index_cmd.py
deebase/cli/init_cmd.py
deebase/cli/migrate_cmd.py
deebase/cli/migration_runner.py
deebase/cli/parser.py
deebase/cli/state.py
deebase/cli/table_cmd.py
deebase/cli/utils.py
deebase/cli/view_cmd.py
deebase/column.py
deebase/database.py
deebase/dataclass_utils.py
deebase/exceptions.py
deebase/py.typed
deebase/table.py
deebase/types.py
deebase/validation.py
deebase/view.py
deebase-0.6.1.dist-info/WHEEL
deebase-0.6.1.dist-info/entry_points.txt
deebase-0.6.1.dist-info/METADATA
deebase-0.6.1.dist-info/RECORD
