Metadata-Version: 2.3
Name: deebase
Version: 0.6.1
Summary: Async SQLAlchemy-based implementation of the fastlite API
Author: Rahul Dave(Credcore)
Author-email: Rahul Dave(Credcore) <rahul@credcore.com>
Requires-Dist: aiosqlite>=0.22.0
Requires-Dist: asyncpg>=0.31.0
Requires-Dist: click>=8.3.1
Requires-Dist: greenlet>=3.3.0
Requires-Dist: sqlalchemy>=2.0.45
Requires-Dist: toml>=0.10.2
Requires-Dist: fastapi>=0.115.0 ; extra == 'api'
Requires-Dist: pydantic>=2.10.0 ; extra == 'api'
Requires-Dist: fastcore>=1.7.0 ; extra == 'api'
Requires-Dist: uvicorn>=0.34.0 ; extra == 'api'
Requires-Dist: jinja2>=3.1.0 ; extra == 'api'
Requires-Dist: python-multipart>=0.0.9 ; extra == 'api'
Requires-Python: >=3.13
Provides-Extra: api
